simplevcf/__init__.py
simplevcf/header.py
simplevcf/snpeff.py
tests/__init__.py
tests/test_header.py
tests/test_reader.py
tests/test_snpeff.py
simplevcf-0.2.0.dist-info/LICENSE
simplevcf-0.2.0.dist-info/METADATA
simplevcf-0.2.0.dist-info/WHEEL
simplevcf-0.2.0.dist-info/top_level.txt
simplevcf-0.2.0.dist-info/RECORD
