Metadata-Version: 2.1
Name: simplevcf
Version: 0.2.0
Summary: A simple VCF parser/weriter
Home-page: https://github.com/informationsea/simplevcf-py
Author: Yasunobu Okamura
Author-email: okamura@informationsea.info
License: UNKNOWN
Platform: UNKNOWN
Classifier: Development Status :: 3 - Alpha
Classifier: Programming Language :: Python :: 3
Classifier: License :: OSI Approved :: Apache Software License
Classifier: Operating System :: OS Independent
Classifier: Topic :: Scientific/Engineering :: Bio-Informatics
Requires-Python: >=3.6
